[
    {
        "id_tmdb": 279320,
        "title": "Devanthakudu",
        "release_date": "1984-04-11",
        "overview": "Devantakudu movie is a murder mystery. In which, chiranjeevi is a college student who is daring and dashing and has a weakness for betting and challenges.Narayana Rao is chiru’s friend in the same college and once he challenges chiru to kill a person and escape without being caught and without proof and this person is a professor.Chiru takes it lightly and tries to play away by acting as if he killed the professor but he is really killed by the time he reaches there and he is accused of he murder.The rest of the movie forms on how he frees himself from the blame and who killed the professor and why?",
        "poster_path": "/4sVGH7YnEYmNsb1tu51cIeBqr2i.jpg",
        "backdrop_path": null,
        "production_companies": [],
        "production_countries": [],
        "spoken_languages": [],
        "budget": 0,
        "revenue": 0,
        "vote_average": 0.0,
        "adult": false,
        "belongs_to_collection": null,
        "homepage": "",
        "imdb_id": "tt0245865",
        "original_language": "en",
        "popularity": 0.151,
        "status": "Released",
        "tagline": "",
        "video": false
    },
    {
        "id_tmdb": 331084,
        "title": "Abisa a los compañeros",
        "release_date": "1980-01-17",
        "overview": "Based on real events in Peru, 1963. A team of revolutionary foreigners planned and pulled a heist on the biggest bank in Peru. The loot helped fund the rural revolution in Concepción, Cusco.",
        "poster_path": "/ucRZSQmmgWfylHF6K7AcmTnLb8l.jpg",
        "backdrop_path": null,
        "production_companies": [
            {
                "name": "Cinematografía Horizonte",
                "id": 48741
            }
        ],
        "production_countries": [
            {
                "iso_3166_1": "PE",
                "name": "Peru"
            }
        ],
        "spoken_languages": [
            {
                "iso_639_1": "es",
                "name": "Español"
            }
        ],
        "budget": 0,
        "revenue": 0,
        "vote_average": 0.0,
        "adult": false,
        "belongs_to_collection": null,
        "homepage": "",
        "imdb_id": "tt0185139",
        "original_language": "es",
        "popularity": 0.149,
        "status": "Released",
        "tagline": "",
        "video": false
    },
    {
        "id_tmdb": 890292,
        "title": "Win 392",
        "release_date": "1984-10-19",
        "overview": "A young Spanish woman who has newly moved to Berlin finds her flirtation with a local guy turn potentially deadly as their night out with his friends reveals a dangerous secret.",
        "poster_path": null,
        "backdrop_path": null,
        "production_companies": [
            {
                "name": "Castets-Campanella",
                "id": 163288
            }
        ],
        "production_countries": [
            {
                "iso_3166_1": "AR",
                "name": "Argentina"
            }
        ],
        "spoken_languages": [
            {
                "iso_639_1": "es",
                "name": "Español"
            }
        ],
        "budget": 0,
        "revenue": 0,
        "vote_average": 0.0,
        "adult": false,
        "belongs_to_collection": null,
        "homepage": "",
        "imdb_id": "tt0304895",
        "original_language": "es",
        "popularity": 0.148,
        "status": "Released",
        "tagline": "",
        "video": false
    },
    {
        "id_tmdb": 839353,
        "title": "Handsome Vagabond",
        "release_date": "1982-01-02",
        "overview": "After serving three years in prison for a murder he didn't commit, an angry streetfighter seeks justice. Two sworn brothers oppose a gang of killers running a gym.",
        "poster_path": "/qXC8OZHz33vzHvmn1aTSxrwCzBB.jpg",
        "backdrop_path": null,
        "production_companies": [],
        "production_countries": [
            {
                "iso_3166_1": "TW",
                "name": "Taiwan"
            }
        ],
        "spoken_languages": [
            {
                "iso_639_1": "zh",
                "name": "普通话"
            }
        ],
        "budget": 0,
        "revenue": 0,
        "vote_average": 0.0,
        "adult": false,
        "belongs_to_collection": null,
        "homepage": "",
        "imdb_id": "tt0201187",
        "original_language": "zh",
        "popularity": 0.148,
        "status": "Released",
        "tagline": "",
        "video": false
    },
    {
        "id_tmdb": 226624,
        "title": "The Antwerp Killer",
        "release_date": "1983-01-02",
        "overview": "The city of Antwerp is being terrorized by a serial killer. When the killer discovers one of his victims is seeing a psychiatrist to overcome her trauma, he goes after her…",
        "poster_path": null,
        "backdrop_path": null,
        "production_companies": [
            {
                "name": "Laura Film",
                "id": 67081
            }
        ],
        "production_countries": [
            {
                "iso_3166_1": "BE",
                "name": "Belgium"
            }
        ],
        "spoken_languages": [
            {
                "iso_639_1": "nl",
                "name": "Nederlands"
            }
        ],
        "budget": 0,
        "revenue": 0,
        "vote_average": 5.0,
        "adult": false,
        "belongs_to_collection": null,
        "homepage": "",
        "imdb_id": "tt0257407",
        "original_language": "nl",
        "popularity": 0.148,
        "status": "Released",
        "tagline": "",
        "video": false
    },
    {
        "id_tmdb": 463142,
        "title": "The Old Shell",
        "release_date": "1980-09-01",
        "overview": "Pandi has been recruited by foreign agents in order to collect information about a military plant where his friend Servet works. To achieve his goal, Pandi blackmails Servet with an old shell, used by Servet to accidentally injure a friend during the military service.",
        "poster_path": "/kEuYgpWr1HTO3Bw8r51j0z8CX8K.jpg",
        "backdrop_path": "/2nsvQJWwPMVyphjHZt5WWhAwFmu.jpg",
        "production_companies": [],
        "production_countries": [
            {
                "iso_3166_1": "AL",
                "name": "Albania"
            }
        ],
        "spoken_languages": [
            {
                "iso_639_1": "sq",
                "name": "shqip"
            }
        ],
        "budget": 0,
        "revenue": 0,
        "vote_average": 7.0,
        "adult": false,
        "belongs_to_collection": null,
        "homepage": "",
        "imdb_id": "tt0295290",
        "original_language": "sq",
        "popularity": 0.141,
        "status": "Released",
        "tagline": "",
        "video": false
    },
    {
        "id_tmdb": 282023,
        "title": "Crab",
        "release_date": "1982-04-22",
        "overview": "Commissioner Leon (Miguel Angel Landa) of the Technical Judicial Police is assigned to the kidnapping of a child of the upper class of Caracas. The details of the kidnapping the attention of Leon, as there is no evidence of violence in the child's home, or witnesses to the abduction. Based on that Leon believes that the hijackers knew the boy and soon begins to suspect several young people from wealthy families of Caracas.",
        "poster_path": "/AlSHmwyvC2mi9LTYiS25TrUakMX.jpg",
        "backdrop_path": null,
        "production_companies": [
            {
                "name": "Gente de Cine",
                "id": 50787
            }
        ],
        "production_countries": [
            {
                "iso_3166_1": "VE",
                "name": "Venezuela"
            }
        ],
        "spoken_languages": [
            {
                "iso_639_1": "es",
                "name": "Español"
            }
        ],
        "budget": 0,
        "revenue": 0,
        "vote_average": 0.0,
        "adult": false,
        "belongs_to_collection": null,
        "homepage": "",
        "imdb_id": "tt0083716",
        "original_language": "es",
        "popularity": 0.124,
        "status": "Released",
        "tagline": "",
        "video": false
    },
    {
        "id_tmdb": 654331,
        "title": "Killing Joke",
        "release_date": "1980-01-01",
        "overview": "Short graduation film.",
        "poster_path": null,
        "backdrop_path": null,
        "production_companies": [
            {
                "name": "Hogeschool Sint-Lukas Brussel",
                "id": 125930
            }
        ],
        "production_countries": [],
        "spoken_languages": [],
        "budget": 0,
        "revenue": 0,
        "vote_average": 0.0,
        "adult": false,
        "belongs_to_collection": null,
        "homepage": "",
        "imdb_id": "tt0270456",
        "original_language": "nl",
        "popularity": 0.121,
        "status": "Released",
        "tagline": "",
        "video": false
    },
    {
        "id_tmdb": 467964,
        "title": "I don't know, I didn't hear, I didn't see",
        "release_date": "1984-05-21",
        "overview": "Night time Sofia in the middle of the 80s. Bus 108 is doing its final route towards the Lyulin neighbourhood. A short altrecation between the passengers finishes with the death of one of them. While investigating the cruel crime the detectives from the militia face people's indifference.",
        "poster_path": null,
        "backdrop_path": null,
        "production_companies": [
            {
                "name": "Boyana Film",
                "id": 15567
            }
        ],
        "production_countries": [
            {
                "iso_3166_1": "BG",
                "name": "Bulgaria"
            }
        ],
        "spoken_languages": [
            {
                "iso_639_1": "bg",
                "name": "български език"
            }
        ],
        "budget": 0,
        "revenue": 0,
        "vote_average": 0.0,
        "adult": false,
        "belongs_to_collection": null,
        "homepage": "",
        "imdb_id": "tt0290013",
        "original_language": "bg",
        "popularity": 0.105,
        "status": "Released",
        "tagline": "",
        "video": false
    },
    {
        "id_tmdb": 971245,
        "title": "刑事案十号",
        "release_date": "1984-01-01",
        "overview": "",
        "poster_path": "/pCSbrywfQ4UyluVU5zaa3RoAPtt.jpg",
        "backdrop_path": null,
        "production_companies": [],
        "production_countries": [],
        "spoken_languages": [],
        "budget": 0,
        "revenue": 0,
        "vote_average": 10.0,
        "adult": false,
        "belongs_to_collection": null,
        "homepage": "",
        "imdb_id": null,
        "original_language": "zh",
        "popularity": 0.104,
        "status": "Released",
        "tagline": "",
        "video": false
    },
    {
        "id_tmdb": 840253,
        "title": "Des larmes comme des couteaux",
        "release_date": "1983-10-26",
        "overview": "",
        "poster_path": "/s2ytorUQgE8nOvSINP2zhRqgLV8.jpg",
        "backdrop_path": null,
        "production_companies": [
            {
                "name": "Antenne 2",
                "id": 1117
            },
            {
                "name": "SFP",
                "id": 6849
            }
        ],
        "production_countries": [
            {
                "iso_3166_1": "FR",
                "name": "France"
            }
        ],
        "spoken_languages": [],
        "budget": 0,
        "revenue": 0,
        "vote_average": 0.0,
        "adult": false,
        "belongs_to_collection": null,
        "homepage": "",
        "imdb_id": null,
        "original_language": "fr",
        "popularity": 0.094,
        "status": "Released",
        "tagline": "",
        "video": false
    },
    {
        "id_tmdb": 748003,
        "title": "Der tote Onkel",
        "release_date": "1982-10-30",
        "overview": "Joseph von Träubesser is a scion of a wealthy aristocratic family. He's not satisfied with idle bliss but is ambitious and tries to become a good painter. His family and especially his nephew Leonid, who could be taken for his twin, think he's cracked.  Fabian Cabanas, a famous painter, isn't at all pleased with his life. Apion Herbst, a postman and spiritualist, holds séances when off duty and helps Fabian to a new body. And Joseph too profits from this séance.",
        "poster_path": null,
        "backdrop_path": null,
        "production_companies": [
            {
                "name": "Thalia-Film",
                "id": 30630
            },
            {
                "name": "ORF",
                "id": 3391
            }
        ],
        "production_countries": [
            {
                "iso_3166_1": "AT",
                "name": "Austria"
            }
        ],
        "spoken_languages": [
            {
                "iso_639_1": "de",
                "name": "Deutsch"
            }
        ],
        "budget": 0,
        "revenue": 0,
        "vote_average": 0.0,
        "adult": false,
        "belongs_to_collection": null,
        "homepage": "",
        "imdb_id": "tt13107128",
        "original_language": "de",
        "popularity": 0.089,
        "status": "Released",
        "tagline": "A modern fantasy",
        "video": false
    },
    {
        "id_tmdb": 632232,
        "title": "Who Killed the Lindbergh Baby?",
        "release_date": "1982-12-10",
        "overview": "Bruno Richard Hauptmann was executed in 1936 for the kidnapping and murder of the infant son of pioneering aviator and American hero Charles Lindbergh. This documentary examines lingering doubts about the justice of his conviction. (1982)",
        "poster_path": "/mXX1F4lInlLCKHRXz0xqmRTUIeT.jpg",
        "backdrop_path": null,
        "production_companies": [
            {
                "name": "BBC",
                "id": 3324
            }
        ],
        "production_countries": [
            {
                "iso_3166_1": "GB",
                "name": "United Kingdom"
            }
        ],
        "spoken_languages": [
            {
                "iso_639_1": "en",
                "name": "English"
            }
        ],
        "budget": 0,
        "revenue": 0,
        "vote_average": 0.0,
        "adult": false,
        "belongs_to_collection": null,
        "homepage": "",
        "imdb_id": null,
        "original_language": "en",
        "popularity": 0.085,
        "status": "Released",
        "tagline": "",
        "video": false
    },
    {
        "id_tmdb": 931083,
        "title": "She an",
        "release_date": "1983-01-01",
        "overview": "",
        "poster_path": "/4o9ra7pjy3XVrCkrw5rLiXMYxkM.jpg",
        "backdrop_path": "/fX4cwfRRqgzlUfrYIKz5nB77jdb.jpg",
        "production_companies": [
            {
                "name": "Emei Film Studio",
                "id": 30324
            }
        ],
        "production_countries": [
            {
                "iso_3166_1": "CN",
                "name": "China"
            }
        ],
        "spoken_languages": [
            {
                "iso_639_1": "zh",
                "name": "普通话"
            }
        ],
        "budget": 0,
        "revenue": 0,
        "vote_average": 0.0,
        "adult": false,
        "belongs_to_collection": null,
        "homepage": "",
        "imdb_id": "tt7950182",
        "original_language": "zh",
        "popularity": 0.081,
        "status": "Released",
        "tagline": "",
        "video": false
    },
    {
        "id_tmdb": 76440,
        "title": "1958",
        "release_date": "1980-08-22",
        "overview": "We follow the rootless Sinsen gang in good times and bad. A life that consists of rock concerts, hut trips, amusement park visits and car thefts. The year is 1958, when the Americans launched the Explorer and the Russians Sputnik III. However, these events do not interest the youthful persons in this film, the members of the \"Sinsen gang\". For them, it is far more important to know which rock hits are on top on Top Twenty on Radio Luxembourg, and to have seen the latest film with Elvis. The most important is to be accepted by the gang, to be loyal to your pals, and for a very few to be prepared for school",
        "poster_path": "/ncMTsw04pBX7wBEPrVC7YL3DPg3.jpg",
        "backdrop_path": null,
        "production_companies": [
            {
                "name": "Norsk Film",
                "id": 12984
            }
        ],
        "production_countries": [
            {
                "iso_3166_1": "NO",
                "name": "Norway"
            }
        ],
        "spoken_languages": [],
        "budget": 0,
        "revenue": 0,
        "vote_average": 3.0,
        "adult": false,
        "belongs_to_collection": null,
        "homepage": "",
        "imdb_id": "tt0080314",
        "original_language": "no",
        "popularity": 0.08,
        "status": "Released",
        "tagline": "",
        "video": false
    },
    {
        "id_tmdb": 1298684,
        "title": "Šanca",
        "release_date": "1983-01-01",
        "overview": "",
        "poster_path": null,
        "backdrop_path": null,
        "production_companies": [
            {
                "name": "Československá televízia Bratislava",
                "id": 28449
            }
        ],
        "production_countries": [
            {
                "iso_3166_1": "XC",
                "name": "Czechoslovakia"
            }
        ],
        "spoken_languages": [
            {
                "iso_639_1": "sk",
                "name": "Slovenčina"
            }
        ],
        "budget": 0,
        "revenue": 0,
        "vote_average": 0.0,
        "adult": false,
        "belongs_to_collection": null,
        "homepage": "",
        "imdb_id": "tt6461404",
        "original_language": "sk",
        "popularity": 0.062,
        "status": "Released",
        "tagline": "",
        "video": false
    },
    {
        "id_tmdb": 191822,
        "title": "Stridura",
        "release_date": "1980-01-01",
        "overview": "In a desolated world, a martyr is steered by a man giving orders from a control room. His henchmen torture the resistance fighter. Are the parts played by victim and hangman defined as clearly as it seems? Ange Leccia offers a political reflection about the power of images and their manipulative force. —ubu.com",
        "poster_path": null,
        "backdrop_path": null,
        "production_companies": [
            {
                "name": "GREC",
                "id": 80377
            }
        ],
        "production_countries": [
            {
                "iso_3166_1": "FR",
                "name": "France"
            }
        ],
        "spoken_languages": [
            {
                "iso_639_1": "xx",
                "name": "No Language"
            }
        ],
        "budget": 0,
        "revenue": 0,
        "vote_average": 4.0,
        "adult": false,
        "belongs_to_collection": null,
        "homepage": "",
        "imdb_id": "tt0320535",
        "original_language": "co",
        "popularity": 0.053,
        "status": "Released",
        "tagline": "",
        "video": false
    },
    {
        "id_tmdb": 582486,
        "title": "The Black Mask",
        "release_date": "1980-01-01",
        "overview": "",
        "poster_path": "/hFI3WXqHUtIOZWabp7oOFrO6HzQ.jpg",
        "backdrop_path": null,
        "production_companies": [
            {
                "name": "Xi'an Film Studio",
                "id": 4582
            },
            {
                "name": "Kunming Film Studio",
                "id": 186745
            }
        ],
        "production_countries": [
            {
                "iso_3166_1": "CN",
                "name": "China"
            }
        ],
        "spoken_languages": [
            {
                "iso_639_1": "zh",
                "name": "普通话"
            }
        ],
        "budget": 0,
        "revenue": 0,
        "vote_average": 0.0,
        "adult": false,
        "belongs_to_collection": null,
        "homepage": "",
        "imdb_id": "tt0339124",
        "original_language": "zh",
        "popularity": 0.043,
        "status": "Released",
        "tagline": "",
        "video": false
    },
    {
        "id_tmdb": 712760,
        "title": "Portrait of an Assassin",
        "release_date": "1983-09-30",
        "overview": "Shot on Super 8 film in 1983 (as a college project), this political-thriller was made on the campus of Rutgers University in Newark, New Jersey. The movie takes place in Canada, and is the story of a hit man (played by Peter Coston) hired to take out a controversial Canadian politician.",
        "poster_path": "/3L5qcHSDRYXvKWJki1wnfHfH4yR.jpg",
        "backdrop_path": "/cnMwGPkkvZHiOfdUK1z1MC3f94W.jpg",
        "production_companies": [
            {
                "name": "Carlos Garcia Productions",
                "id": 135157
            }
        ],
        "production_countries": [],
        "spoken_languages": [],
        "budget": 300,
        "revenue": 0,
        "vote_average": 8.0,
        "adult": false,
        "belongs_to_collection": null,
        "homepage": "",
        "imdb_id": "tt10217258",
        "original_language": "en",
        "popularity": 0.038,
        "status": "Released",
        "tagline": "",
        "video": false
    },
    {
        "id_tmdb": 1250820,
        "title": "东方剑",
        "release_date": "1982-02-27",
        "overview": "",
        "poster_path": "/aV4VdFVcfIbGUmiRIXE4Y19AUe6.jpg",
        "backdrop_path": "/x66sWi1uUMliQttvWtyHthpl5io.jpg",
        "production_companies": [
            {
                "name": "珠江电影制片厂",
                "id": 115186
            }
        ],
        "production_countries": [
            {
                "iso_3166_1": "CN",
                "name": "China"
            }
        ],
        "spoken_languages": [],
        "budget": 0,
        "revenue": 0,
        "vote_average": 0.0,
        "adult": false,
        "belongs_to_collection": null,
        "homepage": "",
        "imdb_id": "tt0346886",
        "original_language": "zh",
        "popularity": 0.036,
        "status": "Released",
        "tagline": "",
        "video": false
    },
    {
        "id_tmdb": 840236,
        "title": "Battling le ténébreux",
        "release_date": "1984-02-08",
        "overview": "",
        "poster_path": "/s42HW49miJae7FnAQ41aEDHIUuD.jpg",
        "backdrop_path": null,
        "production_companies": [
            {
                "name": "Antenne 2",
                "id": 1117
            },
            {
                "name": "SFP",
                "id": 6849
            }
        ],
        "production_countries": [
            {
                "iso_3166_1": "FR",
                "name": "France"
            }
        ],
        "spoken_languages": [],
        "budget": 0,
        "revenue": 0,
        "vote_average": 0.0,
        "adult": false,
        "belongs_to_collection": null,
        "homepage": "",
        "imdb_id": "tt0310724",
        "original_language": "fr",
        "popularity": 0.029,
        "status": "Released",
        "tagline": "",
        "video": false
    },
    {
        "id_tmdb": 1395595,
        "title": "Hanggang sa Huling Bala",
        "release_date": "1984-04-21",
        "overview": "A suspended Cebu cop travels to Manila to take vengeance to the ones that caused his daughter's death.",
        "poster_path": null,
        "backdrop_path": null,
        "production_companies": [],
        "production_countries": [],
        "spoken_languages": [
            {
                "iso_639_1": "tl",
                "name": ""
            }
        ],
        "budget": 0,
        "revenue": 0,
        "vote_average": 0.0,
        "adult": false,
        "belongs_to_collection": null,
        "homepage": "",
        "imdb_id": "tt1532521",
        "original_language": "tl",
        "popularity": 0.011,
        "status": "Released",
        "tagline": "",
        "video": false
    },
    {
        "id_tmdb": 1156409,
        "title": "Callejón oscuro",
        "release_date": "1983-01-01",
        "overview": "A violent blind man wanders through the center of Lima, upon entering a restaurant he causes an incident with the public and the employees.",
        "poster_path": "/4EHnWbkwZad6FkeiLGIKPKadXGT.jpg",
        "backdrop_path": "/qMFAhTdGs9DuYnHcNt8XEMKJRzY.jpg",
        "production_companies": [],
        "production_countries": [
            {
                "iso_3166_1": "PE",
                "name": "Peru"
            }
        ],
        "spoken_languages": [
            {
                "iso_639_1": "es",
                "name": "Español"
            }
        ],
        "budget": 0,
        "revenue": 0,
        "vote_average": 0.0,
        "adult": false,
        "belongs_to_collection": null,
        "homepage": "",
        "imdb_id": null,
        "original_language": "es",
        "popularity": 0.01,
        "status": "Released",
        "tagline": "",
        "video": false
    },
    {
        "id_tmdb": 404364,
        "title": "Goldrunner",
        "release_date": "1980-01-01",
        "overview": "A madman kidnaps an innocent child and only an ex-race car driver can deliver the ransom, a fortune in gold, in time.",
        "poster_path": "/wj3v6K4xxqIxSlBfY11wbfQRPPk.jpg",
        "backdrop_path": null,
        "production_companies": [
            {
                "name": "Losee Pictures",
                "id": 134309
            }
        ],
        "production_countries": [
            {
                "iso_3166_1": "US",
                "name": "United States of America"
            }
        ],
        "spoken_languages": [
            {
                "iso_639_1": "en",
                "name": "English"
            }
        ],
        "budget": 0,
        "revenue": 0,
        "vote_average": 0.0,
        "adult": false,
        "belongs_to_collection": null,
        "homepage": "",
        "imdb_id": "tt0459522",
        "original_language": "en",
        "popularity": 0.002,
        "status": "Released",
        "tagline": "",
        "video": false
    },
    {
        "id_tmdb": 1361974,
        "title": "The Trial of Richard III",
        "release_date": "1984-11-04",
        "overview": "A modern trial by jury at the Old Bailey of one of the most famous events in English history.  Conducted on the afternoon and evening of 21st February, 1984, it was held almost 500 years after the death of the last of the Plantagenet Kings, King Richard III, on Bosworth Field, the last of the English monarchs to die in battle.  The charges are that King Richard III did, in or about the month of August, 1483, in the Tower of London, murder Prince Edward, Prince of Wales, and Prince Richard, Duke of York.  Presiding over the case is Lord Elwyn-Jones, the former Lord Chancellor, and he is ably supported by two of Britain’s leading criminal Queen’s Counsels.  A fascinating trial which presents evidence which offers the viewer the opportunity to join the jury in weighing the evidence and reaching his or her own verdict before discovering that of the television jury.",
        "poster_path": "/6UjGy4oOWzT3Z2TDPxoHMyj2jJa.jpg",
        "backdrop_path": "/mH3pSi0IbP8ICHYgZgDyJP0oDvB.jpg",
        "production_companies": [
            {
                "name": "LWT",
                "id": 6197
            }
        ],
        "production_countries": [
            {
                "iso_3166_1": "GB",
                "name": "United Kingdom"
            }
        ],
        "spoken_languages": [
            {
                "iso_639_1": "en",
                "name": "English"
            }
        ],
        "budget": 0,
        "revenue": 0,
        "vote_average": 0.0,
        "adult": false,
        "belongs_to_collection": null,
        "homepage": "",
        "imdb_id": "tt12071370",
        "original_language": "en",
        "popularity": 0.001,
        "status": "Released",
        "tagline": "",
        "video": false
    },
    {
        "id_tmdb": 1309143,
        "title": "Bergman a Bergman, detektivní kancelář",
        "release_date": "1984-01-01",
        "overview": "",
        "poster_path": null,
        "backdrop_path": null,
        "production_companies": [
            {
                "name": "Československá televize Praha",
                "id": 18199
            },
            {
                "name": "Filmové studio Barrandov",
                "id": 1931
            }
        ],
        "production_countries": [
            {
                "iso_3166_1": "XC",
                "name": "Czechoslovakia"
            }
        ],
        "spoken_languages": [
            {
                "iso_639_1": "cs",
                "name": "Český"
            }
        ],
        "budget": 0,
        "revenue": 0,
        "vote_average": 0.0,
        "adult": false,
        "belongs_to_collection": null,
        "homepage": "",
        "imdb_id": "tt8249698",
        "original_language": "cs",
        "popularity": 0.001,
        "status": "Released",
        "tagline": "",
        "video": false
    },
    {
        "id_tmdb": 1259367,
        "title": "Jack the Ripper: The Final Solution",
        "release_date": "1980-01-01",
        "overview": "In an attempt to solve the mystery, Stephen Knight concluded that five women-Mary Ann Nichols, Annie Chapman, Elizabeth Stride, Catherine Eddowes, and Mary Jane Kelly-were murdered in 1888 to cover up a secret marriage between Prince Albert Victor, and Annie Elizabeth Crook, a working class Irish Catholic girl. Knight's main source, Joseph Gorman (Annie Crook's grandson, Walter Sickert's self-proclaimed son with Annie's daughter Alice Margaret Crook), later retracted the story and admitted to the press that it was a hoax.",
        "poster_path": "/kQyNvOd7zlf2lH18BD39E4qTWUo.jpg",
        "backdrop_path": null,
        "production_companies": [
            {
                "name": "Canyon Entertainment",
                "id": 223523
            },
            {
                "name": "RWB TV",
                "id": 223524
            }
        ],
        "production_countries": [
            {
                "iso_3166_1": "AU",
                "name": "Australia"
            }
        ],
        "spoken_languages": [
            {
                "iso_639_1": "en",
                "name": "English"
            }
        ],
        "budget": 0,
        "revenue": 0,
        "vote_average": 0.0,
        "adult": false,
        "belongs_to_collection": null,
        "homepage": "",
        "imdb_id": "tt0333657",
        "original_language": "en",
        "popularity": 0.001,
        "status": "Released",
        "tagline": "",
        "video": false
    },
    {
        "id_tmdb": 1252323,
        "title": "Rockin' with a Bullet",
        "release_date": "1984-01-01",
        "overview": "Crime lords with fancy cars, pretty women and huge bankrolls mix it up around the world. Champagne, cocaine and willing women are the rewards for fast living, but the underworld comes with risks all its own.",
        "poster_path": "/mL17jLKHPdyCGKaUeJJ5PMzdqN5.jpg",
        "backdrop_path": "/c23neWR0vURsqv3sODD1Pse6IAD.jpg",
        "production_companies": [
            {
                "name": "Jazz Urb Entertainment",
                "id": 222159
            }
        ],
        "production_countries": [
            {
                "iso_3166_1": "US",
                "name": "United States of America"
            }
        ],
        "spoken_languages": [],
        "budget": 0,
        "revenue": 0,
        "vote_average": 0.0,
        "adult": false,
        "belongs_to_collection": null,
        "homepage": "",
        "imdb_id": "tt0892348",
        "original_language": "en",
        "popularity": 0.001,
        "status": "Released",
        "tagline": "",
        "video": false
    },
    {
        "id_tmdb": 1152145,
        "title": "Cercado Pelo Ódio",
        "release_date": "1981-07-15",
        "overview": "",
        "poster_path": "/A9Cc4piSprgO03Etuz2csA46gP6.jpg",
        "backdrop_path": null,
        "production_companies": [],
        "production_countries": [
            {
                "iso_3166_1": "BR",
                "name": "Brazil"
            }
        ],
        "spoken_languages": [],
        "budget": 0,
        "revenue": 0,
        "vote_average": 0.0,
        "adult": false,
        "belongs_to_collection": null,
        "homepage": "",
        "imdb_id": "tt0457823",
        "original_language": "pt",
        "popularity": 0.001,
        "status": "Released",
        "tagline": "",
        "video": false
    },
    {
        "id_tmdb": 1108220,
        "title": "Le crime de la maison Grun",
        "release_date": "1984-05-02",
        "overview": "",
        "poster_path": "/sSC4lR69KLEdRMDNHsVboHLOrAI.jpg",
        "backdrop_path": null,
        "production_companies": [
            {
                "name": "FR3",
                "id": 1579
            }
        ],
        "production_countries": [
            {
                "iso_3166_1": "FR",
                "name": "France"
            }
        ],
        "spoken_languages": [],
        "budget": 0,
        "revenue": 0,
        "vote_average": 0.0,
        "adult": false,
        "belongs_to_collection": null,
        "homepage": "",
        "imdb_id": null,
        "original_language": "fr",
        "popularity": 0.001,
        "status": "Released",
        "tagline": "",
        "video": false
    },
    {
        "id_tmdb": 1044550,
        "title": "Inside and Outside the Court Room",
        "release_date": "1980-01-01",
        "overview": "The film tells the story of Shang Qin, the president of the court, who is upright, enforces the law like a mountain, withstood pressure from all parties, and brings the real culprit to justice",
        "poster_path": null,
        "backdrop_path": null,
        "production_companies": [
            {
                "name": "Emei Film Studio",
                "id": 30324
            }
        ],
        "production_countries": [
            {
                "iso_3166_1": "CN",
                "name": "China"
            }
        ],
        "spoken_languages": [
            {
                "iso_639_1": "zh",
                "name": "普通话"
            }
        ],
        "budget": 0,
        "revenue": 0,
        "vote_average": 0.0,
        "adult": false,
        "belongs_to_collection": null,
        "homepage": "",
        "imdb_id": null,
        "original_language": "zh",
        "popularity": 0.001,
        "status": "Released",
        "tagline": "",
        "video": false
    },
    {
        "id_tmdb": 986901,
        "title": "L'enfant des étoiles",
        "release_date": "1984-12-31",
        "overview": "A Feature film by Mohamed Benayat.",
        "poster_path": "/lv60rNQKMiQjREDS04iM5GCezPz.jpg",
        "backdrop_path": null,
        "production_companies": [
            {
                "name": "Alice Productions",
                "id": 190
            },
            {
                "name": "MK2 Films",
                "id": 6274
            }
        ],
        "production_countries": [],
        "spoken_languages": [
            {
                "iso_639_1": "fr",
                "name": "Français"
            }
        ],
        "budget": 0,
        "revenue": 0,
        "vote_average": 0.0,
        "adult": false,
        "belongs_to_collection": null,
        "homepage": "",
        "imdb_id": "tt6750996",
        "original_language": "fr",
        "popularity": 0.001,
        "status": "Released",
        "tagline": "",
        "video": false
    },
    {
        "id_tmdb": 965836,
        "title": "Dokąd, człowieku?",
        "release_date": "1984-10-09",
        "overview": "Prosecutor Kaleta is conducting his latest case. He tries to explain the circumstances of the death of engineer Szymański.",
        "poster_path": "/eFl5O8y1imI4OOGwdlGKR9Ernyl.jpg",
        "backdrop_path": null,
        "production_companies": [],
        "production_countries": [],
        "spoken_languages": [
            {
                "iso_639_1": "pl",
                "name": "Polski"
            }
        ],
        "budget": 0,
        "revenue": 0,
        "vote_average": 0.0,
        "adult": false,
        "belongs_to_collection": null,
        "homepage": "",
        "imdb_id": "tt9869292",
        "original_language": "pl",
        "popularity": 0.001,
        "status": "Released",
        "tagline": "",
        "video": false
    },
    {
        "id_tmdb": 948935,
        "title": "Desafío al coraje",
        "release_date": "1982-01-01",
        "overview": "",
        "poster_path": "/21ATQ6CcmH3EYQHEBFney0dDhNE.jpg",
        "backdrop_path": "/6XH4sgCjATTOMojd5cZXexFaU94.jpg",
        "production_companies": [],
        "production_countries": [
            {
                "iso_3166_1": "AR",
                "name": "Argentina"
            }
        ],
        "spoken_languages": [
            {
                "iso_639_1": "es",
                "name": "Español"
            }
        ],
        "budget": 0,
        "revenue": 0,
        "vote_average": 0.0,
        "adult": false,
        "belongs_to_collection": null,
        "homepage": "",
        "imdb_id": null,
        "original_language": "es",
        "popularity": 0.001,
        "status": "Released",
        "tagline": "",
        "video": false
    },
    {
        "id_tmdb": 945076,
        "title": "Live Better Electrically",
        "release_date": "1982-01-01",
        "overview": "Cut-ups, analog tape loops, celluloid and fire. W.S. Burroughs and Kurt Kren. Performance art and direct animation. These are all part of the experimental films of Marian Wallace.",
        "poster_path": null,
        "backdrop_path": null,
        "production_companies": [
            {
                "name": "Fati Film Production",
                "id": 213415
            },
            {
                "name": "Snakebyte Productions and Entertainment Group",
                "id": 151767
            }
        ],
        "production_countries": [
            {
                "iso_3166_1": "US",
                "name": "United States of America"
            }
        ],
        "spoken_languages": [
            {
                "iso_639_1": "en",
                "name": "English"
            }
        ],
        "budget": 0,
        "revenue": 0,
        "vote_average": 0.0,
        "adult": false,
        "belongs_to_collection": null,
        "homepage": "",
        "imdb_id": null,
        "original_language": "en",
        "popularity": 0.001,
        "status": "Released",
        "tagline": "",
        "video": false
    },
    {
        "id_tmdb": 923052,
        "title": "Szkatulka z Hongkongu",
        "release_date": "1984-01-01",
        "overview": "Gdańsk, 1929. Policeman Bielecki is investigating drugs smuggled into Poland. Meanwhile, private detective Piekarski is looking for the missing daughter of an industrialist, Marta Domaradzka. There are suspicions that her disappearance is related to the drug scandal.",
        "poster_path": null,
        "backdrop_path": null,
        "production_companies": [],
        "production_countries": [],
        "spoken_languages": [
            {
                "iso_639_1": "pl",
                "name": "Polski"
            }
        ],
        "budget": 0,
        "revenue": 0,
        "vote_average": 0.0,
        "adult": false,
        "belongs_to_collection": null,
        "homepage": "",
        "imdb_id": "tt1372300",
        "original_language": "pl",
        "popularity": 0.001,
        "status": "Released",
        "tagline": "",
        "video": false
    },
    {
        "id_tmdb": 921968,
        "title": "Prom do Szwecji",
        "release_date": "1980-06-09",
        "overview": "Szczepan Zadra lives in Sweden. A Pole by origin, he maintains contacts with the country. He works as a representative of an international transport company. Meanwhile, the Polish militia receives signals that valuable icons have been smuggled into Sweden for some time. Szczepan meets Agata, a girl who is on business in Sweden. Agata is doing the Warsaw antiquarian a favor by bringing a small package to Stockholm. Doesn't realize it contains a valuable icon.",
        "poster_path": "/9vEbqULouwEhbSgB5gU6lCCoifs.jpg",
        "backdrop_path": null,
        "production_companies": [],
        "production_countries": [],
        "spoken_languages": [
            {
                "iso_639_1": "pl",
                "name": "Polski"
            }
        ],
        "budget": 0,
        "revenue": 0,
        "vote_average": 0.0,
        "adult": false,
        "belongs_to_collection": null,
        "homepage": "",
        "imdb_id": "tt1360819",
        "original_language": "pl",
        "popularity": 0.001,
        "status": "Released",
        "tagline": "",
        "video": false
    },
    {
        "id_tmdb": 848944,
        "title": "The Mystery R4",
        "release_date": "1982-01-01",
        "overview": "",
        "poster_path": "/eZV9xRCHi20a5Fa3I5sGiFNMAp3.jpg",
        "backdrop_path": "/hlS3yJSUwimMK2s5bmvaXR5O3sO.jpg",
        "production_companies": [
            {
                "name": "Xi'an Film Studio",
                "id": 4582
            }
        ],
        "production_countries": [
            {
                "iso_3166_1": "CN",
                "name": "China"
            }
        ],
        "spoken_languages": [
            {
                "iso_639_1": "zh",
                "name": "普通话"
            }
        ],
        "budget": 0,
        "revenue": 0,
        "vote_average": 0.0,
        "adult": false,
        "belongs_to_collection": null,
        "homepage": "",
        "imdb_id": "tt6574410",
        "original_language": "zh",
        "popularity": 0.001,
        "status": "Released",
        "tagline": "",
        "video": false
    },
    {
        "id_tmdb": 669425,
        "title": "Olle Möller",
        "release_date": "1984-04-20",
        "overview": "When Olle Möller is charged 1959 for the murder of Rut Lind, it becomes Sweden's biggest murder trial of all time. The accused killer Olle Möller is Sweden's most hated man. On March 7, 1941, Möller was sentenced to ten years in prison for attempted rape, assault and manslaughter. He was released conditionally on September 11, 1948 after serving seven years and nine months of the ten-year sentence. Rut Lind disappeared May 26, 1959, and was later found murdered. The indictment against Olle Möller was entirely based on circumstantial evidence and testimony. The court disregarded testimony from Möller's wife and employer, who argued that Möller could not have had the opportunity to do the deed.",
        "poster_path": "/4NPUn1FNuKuI5nOgh8SDer3jzZK.jpg",
        "backdrop_path": "/66q2xxk5hRizYcxVx3CXpdJZQPI.jpg",
        "production_companies": [
            {
                "name": "SVT",
                "id": 2999
            }
        ],
        "production_countries": [
            {
                "iso_3166_1": "SE",
                "name": "Sweden"
            }
        ],
        "spoken_languages": [],
        "budget": 0,
        "revenue": 0,
        "vote_average": 0.0,
        "adult": false,
        "belongs_to_collection": null,
        "homepage": "",
        "imdb_id": "tt11719358",
        "original_language": "sv",
        "popularity": 0.001,
        "status": "Released",
        "tagline": "",
        "video": false
    },
    {
        "id_tmdb": 565870,
        "title": "Chap'la",
        "release_date": "1980-03-19",
        "overview": "",
        "poster_path": "/1SmbOfIZBec00dL0ZoEQvnqsKE1.jpg",
        "backdrop_path": null,
        "production_companies": [
            {
                "name": "Caraïbe Films Compagnie",
                "id": 190343
            }
        ],
        "production_countries": [
            {
                "iso_3166_1": "GP",
                "name": "Guadaloupe"
            }
        ],
        "spoken_languages": [],
        "budget": 0,
        "revenue": 0,
        "vote_average": 0.0,
        "adult": false,
        "belongs_to_collection": null,
        "homepage": "",
        "imdb_id": "tt0243818",
        "original_language": "fr",
        "popularity": 0.001,
        "status": "Released",
        "tagline": "",
        "video": false
    },
    {
        "id_tmdb": 483616,
        "title": "La muerte insiste",
        "release_date": "1984-01-01",
        "overview": "Octavio Izaga, a prestigious lawyer, middle-aged, single and childless, descendant of a prosperous family from Zulia, is the target of anonymous threats accompanied by failed attempts to assassinate him.",
        "poster_path": "/eIAxfVszqNcmjUdUekcYVAEvyeX.jpg",
        "backdrop_path": null,
        "production_companies": [
            {
                "name": "Producciones JB, C.A.",
                "id": 240736
            }
        ],
        "production_countries": [
            {
                "iso_3166_1": "VE",
                "name": "Venezuela"
            }
        ],
        "spoken_languages": [
            {
                "iso_639_1": "es",
                "name": "Español"
            }
        ],
        "budget": 0,
        "revenue": 0,
        "vote_average": 0.0,
        "adult": false,
        "belongs_to_collection": null,
        "homepage": "",
        "imdb_id": "tt0087753",
        "original_language": "es",
        "popularity": 0.001,
        "status": "Released",
        "tagline": "",
        "video": false
    },
    {
        "id_tmdb": 408201,
        "title": "Du blues dans la tête",
        "release_date": "1981-01-02",
        "overview": "Dan and Carole meet and confess to each other, their desire to leave everything, and to die.  They decide to perform crimes to live without paying. But one day : they commit a murder.",
        "poster_path": null,
        "backdrop_path": null,
        "production_companies": [],
        "production_countries": [
            {
                "iso_3166_1": "FR",
                "name": "France"
            }
        ],
        "spoken_languages": [],
        "budget": 0,
        "revenue": 0,
        "vote_average": 0.0,
        "adult": false,
        "belongs_to_collection": null,
        "homepage": "",
        "imdb_id": null,
        "original_language": "en",
        "popularity": 0.001,
        "status": "Released",
        "tagline": "",
        "video": false
    },
    {
        "id_tmdb": 304684,
        "title": "Zakhmee Insaan",
        "release_date": "1982-01-01",
        "overview": "",
        "poster_path": null,
        "backdrop_path": null,
        "production_companies": [
            {
                "name": "Komal Art International",
                "id": 246063
            }
        ],
        "production_countries": [
            {
                "iso_3166_1": "IN",
                "name": "India"
            }
        ],
        "spoken_languages": [
            {
                "iso_639_1": "hi",
                "name": "हिन्दी"
            }
        ],
        "budget": 0,
        "revenue": 0,
        "vote_average": 0.0,
        "adult": false,
        "belongs_to_collection": null,
        "homepage": "",
        "imdb_id": "tt0370087",
        "original_language": "hi",
        "popularity": 0.001,
        "status": "Released",
        "tagline": "",
        "video": false
    }
]